CHANGELOG.md
LICENSE
MANIFEST.in
README
README.md
setup.cfg
setup.py
ofxclient/__init__.py
ofxclient/account.py
ofxclient/cli.py
ofxclient/client.py
ofxclient/config.py
ofxclient/institution.py
ofxclient/util.py
ofxclient/version.py
ofxclient.egg-info/PKG-INFO
ofxclient.egg-info/SOURCES.txt
ofxclient.egg-info/dependency_links.txt
ofxclient.egg-info/entry_points.txt
ofxclient.egg-info/not-zip-safe
ofxclient.egg-info/requires.txt
ofxclient.egg-info/top_level.txt
tests/__init__.py
tests/account.py
tests/institution.py
tests/ofxconfig.py
tests/secure_config.py